{"song":{"sectionLengths":[],"player1":"bf","notes":[{"sectionNotes":[],"lengthInSteps":16,"typeOfSection":0,"mustHitSection":true},{"sectionNotes":[],"lengthInSteps":16,"typeOfSection":0,"mustHitSection":true},{"sectionNotes":[],"lengthInSteps":16,"typeOfSection":0,"mustHitSection":true},{"sectionNotes":[],"lengthInSteps":16,"typeOfSection":0,"mustHitSection":true},{"sectionNotes":[],"lengthInSteps":16,"typeOfSection":0,"mustHitSection":true},{"sectionNotes":[],"lengthInSteps":16,"typeOfSection":0,"mustHitSection":true},{"sectionNotes":[],"lengthInSteps":16,"typeOfSection":0,"mustHitSection":true},{"sectionNotes":[],"lengthInSteps":16,"typeOfSection":0,"mustHitSection":true},{"sectionNotes":[],"lengthInSteps":16,"typeOfSection":0,"mustHitSection":true},{"sectionNotes":[],"lengthInSteps":16,"typeOfSection":0,"mustHitSection":true},{"sectionNotes":[],"lengthInSteps":16,"typeOfSection":0,"mustHitSection":true},{"sectionNotes":[],"lengthInSteps":16,"typeOfSection":0,"mustHitSection":true},{"sectionNotes":[],"lengthInSteps":16,"typeOfSection":0,"mustHitSection":true},{"sectionNotes":[],"lengthInSteps":16,"typeOfSection":0,"mustHitSection":true},{"sectionNotes":[],"lengthInSteps":16,"typeOfSection":0,"mustHitSection":true},{"sectionNotes":[],"lengthInSteps":16,"typeOfSection":0,"mustHitSection":true},{"sectionNotes":[[24161.6766467066,3,0]],"lengthInSteps":16,"typeOfSection":0,"mustHitSection":false},{"sectionNotes":[[24970.0598802395,0,1257.48502994012],[24431.1377245509,2,0]],"lengthInSteps":16,"typeOfSection":0,"mustHitSection":false},{"sectionNotes":[[26856.2874251497,1,0]],"lengthInSteps":16,"typeOfSection":0,"mustHitSection":false},{"sectionNotes":[[27305.3892215569,2,0],[27844.3113772455,2,179.640718562874],[28473.0538922156,2,0]],"lengthInSteps":16,"typeOfSection":0,"mustHitSection":false},{"sectionNotes":[[28832.3353293413,1,0],[29191.6167664671,2,375],[29640.7185628742,1,853.293413173653]],"lengthInSteps":16,"typeOfSection":0,"mustHitSection":false},{"sectionNotes":[[31257.4850299401,0,0]],"lengthInSteps":16,"typeOfSection":0,"mustHitSection":false},{"sectionNotes":[[31616.7664670659,3,0],[31976.0479041916,1,1437.12574850299]],"lengthInSteps":16,"typeOfSection":0,"mustHitSection":false},{"sectionNotes":[],"lengthInSteps":16,"typeOfSection":0,"mustHitSection":false},{"sectionNotes":[[35658.6826347305,3,0]],"lengthInSteps":16,"typeOfSection":0,"mustHitSection":true},{"sectionNotes":[[36556.8862275449,0,808.383233532934],[36017.9640718563,2,0]],"lengthInSteps":16,"typeOfSection":0,"mustHitSection":true},{"sectionNotes":[[38443.1137724551,2,0]],"lengthInSteps":16,"typeOfSection":0,"mustHitSection":true},{"sectionNotes":[[38802.3952095808,0,0],[39341.3173652695,0,437.5],[39880.2395209581,0,312.5]],"lengthInSteps":16,"typeOfSection":0,"mustHitSection":true},{"sectionNotes":[[40329.3413173653,1,0],[40688.622754491,3,1796.40718562874]],"lengthInSteps":16,"typeOfSection":0,"mustHitSection":true},{"sectionNotes":[[42754.4910179641,2,0]],"lengthInSteps":16,"typeOfSection":0,"mustHitSection":true},{"sectionNotes":[[43473.0538922156,2,449.101796407186],[43473.0538922156,5,449.101796407186],[44191.6167664671,3,404.191616766467],[44191.6167664671,4,404.191616766467]],"lengthInSteps":16,"typeOfSection":0,"mustHitSection":false},{"sectionNotes":[[44910.1796407185,3,437.5],[45628.74251497,2,359.281437125749],[44910.1796407185,4,449.101796407186],[45628.74251497,5,359.281437125749]],"lengthInSteps":16,"typeOfSection":0,"mustHitSection":true},{"sectionNotes":[[46347.3053892215,2,1077.84431137725]],"lengthInSteps":16,"typeOfSection":0,"mustHitSection":false},{"sectionNotes":[[47604.7904191617,1,1886.22754491018]],"lengthInSteps":16,"typeOfSection":0,"mustHitSection":false},{"sectionNotes":[],"lengthInSteps":16,"typeOfSection":0,"mustHitSection":false},{"sectionNotes":[[50479.0419161676,2,0],[51197.6047904191,1,0],[51556.8862275449,2,0]],"lengthInSteps":16,"typeOfSection":0,"mustHitSection":true},{"sectionNotes":[[52095.8083832335,2,1077.84431137725]],"lengthInSteps":16,"typeOfSection":0,"mustHitSection":true},{"sectionNotes":[[53353.2934131736,1,1257.48502994012]],"lengthInSteps":16,"typeOfSection":0,"mustHitSection":true},{"sectionNotes":[[55598.8023952096,1,0],[55958.0838323353,3,0],[55598.8023952096,6,0],[55958.0838323353,4,0]],"lengthInSteps":16,"typeOfSection":0,"mustHitSection":true},{"sectionNotes":[[56137.7245508982,6,0],[56586.8263473054,5,0],[57305.3892215569,7,0],[56137.7245508982,1,0],[56586.8263473054,2,0],[57305.3892215569,0,0]],"lengthInSteps":16,"typeOfSection":0,"mustHitSection":false},{"sectionNotes":[[57574.8502994012,2,0],[57574.8502994012,5,0],[58203.5928143712,1,0],[58742.5149700599,1,0],[58203.5928143712,6,0],[58742.5149700599,6,0]],"lengthInSteps":16,"typeOfSection":0,"mustHitSection":true},{"sectionNotes":[[59101.7964071856,2,0],[60179.6407185628,0,0],[59820.3592814371,3,0],[59101.7964071856,5,0],[59820.3592814371,4,0],[60179.6407185628,7,0]],"lengthInSteps":16,"typeOfSection":0,"mustHitSection":true},{"typeOfSection":0,"sectionNotes":[[60538.9221556886,1,988.023952095808],[61616.7664670658,1,0],[60538.9221556886,6,988.023952095808],[61616.7664670658,6,0]],"lengthInSteps":16,"bpm":120,"changeBPM":false,"mustHitSection":true},{"lengthInSteps":16,"typeOfSection":0,"sectionNotes":[[62065.868263473,3,404.191616766467],[63053.8922155688,3,359.281437125749],[62694.6107784431,2,269.461077844311],[62065.868263473,4,404.191616766467],[62694.6107784431,5,269.461077844311],[63053.8922155688,4,359.281437125749]],"altAnim":false,"bpm":120,"changeBPM":false,"mustHitSection":true},{"lengthInSteps":16,"typeOfSection":0,"sectionNotes":[[63502.994011976,5,898.203592814371],[64491.0179640718,4,0],[63502.994011976,2,898.203592814371],[64491.0179640718,3,0]],"altAnim":false,"bpm":167,"changeBPM":false,"mustHitSection":false},{"sectionNotes":[[64940.119760479,6,224.550898203593],[65389.2215568862,7,179.640718562874],[65748.5029940119,7,0],[64940.119760479,1,224.550898203593],[65389.2215568862,0,179.640718562874],[65748.5029940119,0,0]],"typeOfSection":0,"lengthInSteps":16,"altAnim":false,"mustHitSection":false,"changeBPM":false,"bpm":167},{"sectionNotes":[[66107.7844311377,2,0],[66377.245508982,1,224.550898203593],[66736.5269461078,0,1167.66467065868],[66107.7844311377,5,0],[66377.245508982,6,224.550898203593],[66736.5269461078,7,1167.66467065868]],"typeOfSection":0,"lengthInSteps":16,"altAnim":false,"mustHitSection":true,"changeBPM":false,"bpm":167},{"sectionNotes":[[68532.9341317365,3,359.281437125749],[68532.9341317365,4,359.281437125749]],"typeOfSection":0,"lengthInSteps":16,"altAnim":false,"mustHitSection":true,"changeBPM":false,"bpm":167},{"sectionNotes":[[68982.0359281437,2,0],[69610.7784431137,1,0],[70149.7005988024,1,0],[68982.0359281437,5,0],[69610.7784431137,6,0],[70149.7005988024,6,0]],"typeOfSection":0,"lengthInSteps":16,"altAnim":false,"mustHitSection":true,"changeBPM":false,"bpm":167},{"sectionNotes":[[70598.8023952096,2,0],[71317.3652694611,0,0],[71676.6467065868,3,0],[70598.8023952096,5,0],[71317.3652694611,7,0],[71676.6467065868,4,0]],"typeOfSection":0,"lengthInSteps":16,"altAnim":false,"mustHitSection":true,"changeBPM":false,"bpm":167},{"sectionNotes":[[72035.9281437125,1,988.023952095808],[73113.7724550898,1,0],[72035.9281437125,6,988.023952095809],[73113.7724550898,6,0]],"typeOfSection":0,"lengthInSteps":16,"altAnim":false,"mustHitSection":true,"changeBPM":false,"bpm":167},{"sectionNotes":[[73383.2335329341,2,0],[73562.874251497,3,359.281437125749],[74371.2574850299,1,0],[73383.2335329341,5,0],[73562.874251497,4,359.281437125748],[74371.2574850299,6,0]],"typeOfSection":0,"lengthInSteps":16,"altAnim":false,"mustHitSection":true,"changeBPM":false,"bpm":167},{"sectionNotes":[[74730.5389221557,0,0],[75089.8203592814,2,808.383233532934],[74730.5389221557,7,0],[75089.8203592814,5,808.383233532934]],"typeOfSection":0,"lengthInSteps":16,"altAnim":false,"mustHitSection":true,"changeBPM":false,"bpm":167},{"sectionNotes":[[76167.6646706586,2,0],[76437.125748503,3,179.640718562874],[76706.5868263473,1,179.640718562874],[77065.868263473,2,179.640718562874],[76167.6646706586,5,0],[76437.125748503,4,179.640718562874],[76706.5868263473,6,179.640718562874],[77065.868263473,5,179.640718562874],[77425.1497005988,6,0]],"typeOfSection":0,"lengthInSteps":16,"altAnim":false,"mustHitSection":true,"changeBPM":false,"bpm":167},{"sectionNotes":[[78053.8922155688,0,0],[78323.3532934131,1,1167.66467065868],[77604.7904191616,7,0],[77784.4311377245,5,0],[78053.8922155688,7,0],[78323.3532934131,6,1167.66467065868]],"typeOfSection":0,"lengthInSteps":16,"altAnim":false,"mustHitSection":true,"changeBPM":false,"bpm":167},{"sectionNotes":[[79580.8383233533,0,0],[79940.119760479,2,404.191616766467]],"typeOfSection":0,"lengthInSteps":16,"altAnim":false,"mustHitSection":true,"changeBPM":false,"bpm":167},{"sectionNotes":[[80568.8622754491,3,179.640718562874],[80928.1437125748,0,1077.84431137725]],"typeOfSection":0,"lengthInSteps":16,"altAnim":false,"mustHitSection":true,"changeBPM":false,"bpm":167},{"sectionNotes":[[82185.6287425149,1,179.640718562874]],"typeOfSection":0,"lengthInSteps":16,"altAnim":false,"mustHitSection":true,"changeBPM":false,"bpm":167},{"lengthInSteps":16,"typeOfSection":0,"sectionNotes":[],"altAnim":false,"bpm":167,"changeBPM":false,"mustHitSection":true},{"lengthInSteps":16,"typeOfSection":0,"sectionNotes":[],"altAnim":false,"bpm":167,"changeBPM":false,"mustHitSection":true},{"lengthInSteps":16,"typeOfSection":0,"sectionNotes":[],"altAnim":false,"bpm":167,"changeBPM":false,"mustHitSection":true},{"lengthInSteps":16,"typeOfSection":0,"sectionNotes":[],"altAnim":false,"bpm":167,"changeBPM":false,"mustHitSection":true},{"lengthInSteps":16,"typeOfSection":0,"sectionNotes":[],"altAnim":false,"bpm":167,"changeBPM":false,"mustHitSection":true},{"sectionNotes":[],"typeOfSection":0,"lengthInSteps":16,"altAnim":false,"mustHitSection":true,"changeBPM":false,"bpm":167},{"sectionNotes":[],"typeOfSection":0,"lengthInSteps":16,"altAnim":false,"mustHitSection":true,"changeBPM":false,"bpm":167},{"sectionNotes":[],"typeOfSection":0,"lengthInSteps":16,"altAnim":false,"mustHitSection":true,"changeBPM":false,"bpm":167},{"sectionNotes":[],"typeOfSection":0,"lengthInSteps":16,"altAnim":false,"mustHitSection":true,"changeBPM":false,"bpm":167},{"lengthInSteps":16,"typeOfSection":0,"sectionNotes":[],"altAnim":false,"bpm":167,"changeBPM":false,"mustHitSection":true},{"lengthInSteps":16,"typeOfSection":0,"sectionNotes":[],"altAnim":false,"bpm":167,"changeBPM":false,"mustHitSection":true},{"lengthInSteps":16,"typeOfSection":0,"sectionNotes":[],"altAnim":false,"bpm":167,"changeBPM":false,"mustHitSection":true},{"lengthInSteps":16,"typeOfSection":0,"sectionNotes":[],"altAnim":false,"bpm":167,"changeBPM":false,"mustHitSection":true},{"sectionNotes":[],"typeOfSection":0,"lengthInSteps":16,"altAnim":false,"mustHitSection":true,"changeBPM":false,"bpm":167},{"sectionNotes":[],"typeOfSection":0,"lengthInSteps":16,"altAnim":false,"mustHitSection":true,"changeBPM":false,"bpm":167},{"sectionNotes":[],"typeOfSection":0,"lengthInSteps":16,"altAnim":false,"mustHitSection":true,"changeBPM":false,"bpm":167},{"lengthInSteps":16,"altAnim":false,"typeOfSection":0,"sectionNotes":[],"bpm":167,"changeBPM":false,"mustHitSection":true},{"lengthInSteps":16,"altAnim":false,"typeOfSection":0,"sectionNotes":[],"bpm":167,"changeBPM":false,"mustHitSection":true},{"lengthInSteps":16,"altAnim":false,"typeOfSection":0,"sectionNotes":[],"bpm":167,"changeBPM":false,"mustHitSection":true},{"lengthInSteps":16,"altAnim":false,"typeOfSection":0,"sectionNotes":[],"bpm":167,"changeBPM":false,"mustHitSection":true},{"lengthInSteps":16,"altAnim":false,"typeOfSection":0,"sectionNotes":[],"bpm":167,"changeBPM":false,"mustHitSection":true},{"lengthInSteps":16,"altAnim":false,"typeOfSection":0,"sectionNotes":[],"bpm":167,"changeBPM":false,"mustHitSection":true}],"player2":"dad","song":"you-are-stronger","validScore":true,"sections":0,"needsVoices":true,"speed":1.7,"bpm":167}}