{
	"song": {
		"player1": "bf-metaverse",
		"player2": "pico-metaverse",
		"notes": [
			{
				"lengthInSteps": 16,
				"sectionNotes": [],
				"mustHitSection": false
			},
			{
				"lengthInSteps": 16,
				"sectionNotes": [
					[
						1371.42857142857,
						3,
						0
					],
					[
						2057.14285714286,
						1,
						0
					],
					[
						2228.57142857143,
						0,
						0
					],
					[
						2571.42857142857,
						1,
						0
					],
					[
						1714.28571428571,
						0,
						0
					],
					[
						1885.71428571429,
						3,
						0
					]
				],
				"mustHitSection": false
			},
			{
				"lengthInSteps": 16,
				"sectionNotes": [
					[
						2742.85714285714,
						3,
						0
					],
					[
						3085.71428571429,
						2,
						0
					],
					[
						3257.14285714286,
						0,
						0
					],
					[
						3600,
						3,
						257.142857142857
					],
					[
						3942.85714285714,
						3,
						0
					]
				],
				"mustHitSection": false
			},
			{
				"lengthInSteps": 16,
				"sectionNotes": [
					[
						4114.28571428571,
						3,
						0
					],
					[
						4800,
						3,
						0
					],
					[
						5142.85714285714,
						2,
						0
					],
					[
						5314.28571428571,
						2,
						0
					],
					[
						4457.14285714286,
						1,
						0
					],
					[
						4971.42857142857,
						3,
						0
					]
				],
				"mustHitSection": false
			},
			{
				"lengthInSteps": 16,
				"sectionNotes": [
					[
						5828.57142857143,
						0,
						0
					],
					[
						6171.42857142857,
						2,
						0
					],
					[
						6342.85714285714,
						0,
						0
					],
					[
						6600,
						2,
						0
					],
					[
						6685.71428571429,
						0,
						0
					],
					[
						5485.71428571429,
						1,
						0
					]
				],
				"mustHitSection": false
			},
			{
				"lengthInSteps": 16,
				"sectionNotes": [
					[
						6857.14285714286,
						1,
						85.7142857142857
					],
					[
						7200,
						3,
						171.428571428571
					],
					[
						8057.14285714286,
						1,
						257.142857142857
					],
					[
						7542.85714285714,
						0,
						85.7142857142857
					],
					[
						8057.14285714286,
						6,
						0
					],
					[
						7371.42857142857,
						4,
						0
					],
					[
						7542.85714285714,
						7,
						0
					],
					[
						7714.28571428571,
						4,
						0
					]
				],
				"mustHitSection": true
			},
			{
				"lengthInSteps": 16,
				"sectionNotes": [
					[
						8400,
						3,
						171.428571428571
					],
					[
						8742.85714285714,
						0,
						85.7142857142857
					],
					[
						9085.71428571428,
						2,
						342.857142857143
					],
					[
						8400,
						6,
						0
					],
					[
						8742.85714285714,
						4,
						0
					],
					[
						8914.28571428571,
						7,
						0
					],
					[
						9085.71428571428,
						4,
						0
					],
					[
						9428.57142857143,
						5,
						0
					]
				],
				"mustHitSection": true
			},
			{
				"lengthInSteps": 16,
				"sectionNotes": [
					[
						10800,
						7,
						600
					],
					[
						9600,
						5,
						471.428571428571
					],
					[
						10114.2857142857,
						0,
						0
					],
					[
						10285.7142857143,
						3,
						0
					],
					[
						10457.1428571429,
						0,
						0
					],
					[
						10800,
						2,
						0
					]
				],
				"mustHitSection": false
			},
			{
				"lengthInSteps": 16,
				"sectionNotes": [
					[
						11485.7142857143,
						5,
						771.428571428571
					],
					[
						11485.7142857143,
						0,
						0
					],
					[
						11828.5714285714,
						0,
						0
					],
					[
						11142.8571428571,
						2,
						0
					],
					[
						12171.4285714286,
						1,
						0
					],
					[
						11314.2857142857,
						1,
						0
					]
				],
				"mustHitSection": false
			},
			{
				"lengthInSteps": 16,
				"sectionNotes": [
					[
						12857.1428571429,
						0,
						0
					],
					[
						13542.8571428571,
						3,
						0
					],
					[
						13028.5714285714,
						1,
						0
					]
				],
				"mustHitSection": true
			},
			{
				"lengthInSteps": 16,
				"sectionNotes": [
					[
						13885.7142857143,
						0,
						0
					],
					[
						14228.5714285714,
						2,
						0
					],
					[
						14571.4285714286,
						3,
						0
					],
					[
						14914.2857142857,
						3,
						771.428571428571
					]
				],
				"mustHitSection": true
			},
			{
				"lengthInSteps": 16,
				"sectionNotes": [
					[
						15942.8571428571,
						3,
						0
					],
					[
						16285.7142857143,
						0,
						600
					]
				],
				"mustHitSection": true
			},
			{
				"lengthInSteps": 16,
				"sectionNotes": [
					[
						17142.8571428571,
						1,
						0
					],
					[
						17485.7142857143,
						3,
						0
					]
				],
				"mustHitSection": true
			},
			{
				"lengthInSteps": 16,
				"sectionNotes": [
					[
						17828.5714285714,
						6,
						0
					],
					[
						18342.8571428571,
						4,
						771.428571428571
					],
					[
						18000,
						2,
						0
					],
					[
						18342.8571428571,
						3,
						0
					],
					[
						18685.7142857143,
						2,
						0
					],
					[
						18857.1428571429,
						3,
						0
					]
				],
				"mustHitSection": false
			},
			{
				"lengthInSteps": 16,
				"sectionNotes": [
					[
						19371.4285714286,
						3,
						0
					],
					[
						19714.2857142857,
						0,
						0
					],
					[
						19714.2857142857,
						4,
						428.571428571429
					],
					[
						20228.5714285714,
						7,
						257.142857142857
					],
					[
						20057.1428571429,
						3,
						0
					],
					[
						20228.5714285714,
						2,
						0
					]
				],
				"mustHitSection": false
			},
			{
				"lengthInSteps": 16,
				"sectionNotes": [
					[
						20571.4285714286,
						2,
						942.857142857143
					],
					[
						21771.4285714286,
						1,
						1200
					],
					[
						20742.8571428571,
						6,
						0
					],
					[
						21085.7142857143,
						7,
						0
					],
					[
						21771.4285714286,
						5,
						0
					],
					[
						21428.5714285714,
						5,
						0
					],
					[
						21257.1428571429,
						4,
						0
					]
				],
				"mustHitSection": true
			},
			{
				"lengthInSteps": 16,
				"sectionNotes": [
					[
						22114.2857142857,
						5,
						0
					],
					[
						22285.7142857143,
						4,
						0
					],
					[
						22628.5714285714,
						6,
						0
					],
					[
						22800,
						5,
						0
					],
					[
						23142.8571428571,
						7,
						0
					]
				],
				"mustHitSection": true
			},
			{
				"lengthInSteps": 16,
				"sectionNotes": [
					[
						23828.5714285714,
						3,
						0
					],
					[
						24514.2857142857,
						3,
						0
					],
					[
						24171.4285714286,
						0,
						0
					]
				],
				"mustHitSection": true
			},
			{
				"lengthInSteps": 16,
				"sectionNotes": [
					[
						24857.1428571429,
						2,
						685.714285714286
					]
				],
				"mustHitSection": true
			},
			{
				"lengthInSteps": 16,
				"sectionNotes": [
					[
						26914.2857142857,
						1,
						0
					],
					[
						27257.1428571429,
						3,
						0
					],
					[
						26571.4285714286,
						0,
						0
					]
				],
				"mustHitSection": true
			},
			{
				"lengthInSteps": 16,
				"sectionNotes": [
					[
						27600,
						3,
						428.571428571429
					],
					[
						28457.1428571429,
						3,
						171.428571428571
					]
				],
				"mustHitSection": true
			},
			{
				"lengthInSteps": 16,
				"sectionNotes": [
					[
						29314.2857142857,
						6,
						771.428571428571
					],
					[
						28800,
						4,
						385.714285714286
					],
					[
						28971.4285714286,
						1,
						0
					],
					[
						29314.2857142857,
						0,
						0
					],
					[
						29657.1428571429,
						0,
						0
					],
					[
						30000,
						2,
						0
					]
				],
				"mustHitSection": false
			},
			{
				"lengthInSteps": 16,
				"sectionNotes": [
					[
						30685.7142857143,
						5,
						428.571428571429
					],
					[
						31200,
						4,
						257.142857142857
					],
					[
						30342.8571428571,
						2,
						0
					],
					[
						30685.7142857143,
						0,
						0
					],
					[
						31028.5714285714,
						1,
						0
					],
					[
						31200,
						3,
						0
					],
					[
						31371.4285714286,
						1,
						0
					]
				],
				"mustHitSection": false
			},
			{
				"lengthInSteps": 16,
				"sectionNotes": [
					[
						31714.2857142857,
						7,
						0
					],
					[
						32057.1428571429,
						4,
						0
					],
					[
						32228.5714285714,
						7,
						0
					],
					[
						32571.4285714286,
						4,
						0
					],
					[
						31542.8571428571,
						3,
						600
					],
					[
						32228.5714285714,
						2,
						428.571428571428
					],
					[
						32742.8571428571,
						0,
						600
					]
				],
				"mustHitSection": true
			},
			{
				"lengthInSteps": 16,
				"sectionNotes": [
					[
						33428.5714285714,
						3,
						428.571428571429
					],
					[
						33942.8571428571,
						1,
						85.7142857142857
					],
					[
						32914.2857142857,
						6,
						0
					],
					[
						33257.1428571429,
						7,
						0
					],
					[
						33942.8571428571,
						4,
						0
					],
					[
						33600,
						5,
						0
					]
				],
				"mustHitSection": true
			},
			{
				"lengthInSteps": 16,
				"sectionNotes": [
					[
						34285.7142857143,
						1,
						1114.28571428571
					],
					[
						35485.7142857143,
						2,
						857.142857142857
					],
					[
						35485.7142857143,
						6,
						0
					],
					[
						34800,
						7,
						0
					],
					[
						35142.8571428571,
						5,
						0
					],
					[
						34971.4285714286,
						4,
						0
					]
				],
				"mustHitSection": true
			},
			{
				"lengthInSteps": 16,
				"sectionNotes": [
					[
						36514.2857142857,
						3,
						0
					],
					[
						36857.1428571429,
						1,
						0
					],
					[
						35828.5714285714,
						6,
						0
					],
					[
						36171.4285714286,
						7,
						0
					],
					[
						36342.8571428571,
						4,
						0
					],
					[
						36857.1428571429,
						5,
						0
					],
					[
						36514.2857142857,
						6,
						0
					]
				],
				"mustHitSection": true
			},
			{
				"lengthInSteps": 16,
				"sectionNotes": [
					[
						37028.5714285714,
						3,
						0
					],
					[
						38228.5714285714,
						1,
						0
					],
					[
						37371.4285714286,
						3,
						0
					],
					[
						37542.8571428572,
						7,
						0
					],
					[
						37714.2857142857,
						4,
						0
					],
					[
						37885.7142857143,
						5,
						0
					],
					[
						38228.5714285714,
						7,
						0
					],
					[
						37714.2857142857,
						1,
						0
					],
					[
						38057.1428571429,
						0,
						0
					]
				],
				"mustHitSection": true
			},
			{
				"lengthInSteps": 16,
				"sectionNotes": [
					[
						38571.4285714286,
						3,
						428.571428571429
					],
					[
						39428.5714285714,
						1,
						171.428571428571
					],
					[
						38485.7142857143,
						7,
						0
					],
					[
						38914.2857142857,
						6,
						0
					],
					[
						39085.7142857143,
						4,
						0
					],
					[
						39428.5714285714,
						4,
						0
					],
					[
						39600,
						5,
						0
					]
				],
				"mustHitSection": true
			},
			{
				"lengthInSteps": 16,
				"sectionNotes": [
					[
						39771.4285714286,
						5,
						942.857142857143
					],
					[
						39771.4285714286,
						0,
						0
					],
					[
						40800,
						1,
						0
					],
					[
						40971.4285714286,
						7,
						342.857142857143
					],
					[
						40114.2857142857,
						2,
						0
					],
					[
						40457.1428571429,
						0,
						0
					]
				],
				"mustHitSection": false
			},
			{
				"lengthInSteps": 16,
				"sectionNotes": [
					[
						41657.1428571429,
						7,
						342.857142857143
					],
					[
						42171.4285714286,
						6,
						257.142857142857
					],
					[
						41657.1428571429,
						0,
						0
					],
					[
						41828.5714285714,
						3,
						0
					],
					[
						41142.8571428572,
						0,
						0
					],
					[
						41485.7142857143,
						3,
						0
					],
					[
						42342.8571428572,
						1,
						0
					],
					[
						42171.4285714286,
						2,
						0
					]
				],
				"mustHitSection": false
			},
			{
				"lengthInSteps": 16,
				"sectionNotes": [
					[
						42514.2857142857,
						4,
						1628.57142857143
					],
					[
						42685.7142857143,
						1,
						0
					],
					[
						43200,
						0,
						0
					],
					[
						43542.8571428572,
						2,
						0
					],
					[
						43028.5714285714,
						3,
						0
					]
				],
				"mustHitSection": false
			},
			{
				"lengthInSteps": 16,
				"sectionNotes": [
					[
						44400,
						0,
						0
					],
					[
						44914.2857142857,
						3,
						0
					],
					[
						44571.4285714286,
						0,
						85.7142857142857
					],
					[
						43885.7142857143,
						4,
						0
					],
					[
						44914.2857142857,
						6,
						0
					],
					[
						44057.1428571429,
						7,
						0
					],
					[
						44571.4285714286,
						7,
						0
					],
					[
						45085.7142857143,
						4,
						0
					],
					[
						44228.5714285714,
						5,
						0
					]
				],
				"mustHitSection": true
			},
			{
				"lengthInSteps": 16,
				"sectionNotes": [
					[
						45257.1428571429,
						1,
						257.142857142857
					],
					[
						45771.4285714286,
						1,
						0
					],
					[
						46114.2857142857,
						3,
						0
					],
					[
						46457.1428571429,
						2,
						0
					]
				],
				"mustHitSection": true
			},
			{
				"lengthInSteps": 16,
				"sectionNotes": [
					[
						46800,
						3,
						0
					],
					[
						47142.8571428572,
						0,
						0
					],
					[
						47485.7142857143,
						3,
						428.571428571429
					]
				],
				"mustHitSection": true
			},
			{
				"lengthInSteps": 16,
				"sectionNotes": [
					[
						48171.4285714286,
						0,
						0
					],
					[
						49028.5714285714,
						2,
						85.7142857142857
					],
					[
						48514.2857142857,
						3,
						0
					],
					[
						48685.7142857143,
						0,
						257.142857142857
					]
				],
				"mustHitSection": true
			},
			{
				"lengthInSteps": 16,
				"sectionNotes": [
					[
						49885.7142857143,
						3,
						0
					],
					[
						50228.5714285714,
						1,
						428.571428571429
					],
					[
						49371.4285714286,
						1,
						0
					]
				],
				"mustHitSection": true
			},
			{
				"lengthInSteps": 16,
				"sectionNotes": [
					[
						50742.8571428572,
						3,
						0
					],
					[
						51257.1428571429,
						1,
						771.428571428571
					],
					[
						51257.1428571429,
						4,
						0
					],
					[
						51428.5714285714,
						7,
						0
					],
					[
						51600,
						5,
						0
					],
					[
						51942.8571428572,
						6,
						0
					]
				],
				"mustHitSection": true
			},
			{
				"lengthInSteps": 16,
				"sectionNotes": [
					[
						52628.5714285714,
						1,
						257.142857142857
					],
					[
						52971.4285714286,
						3,
						0
					],
					[
						52628.5714285714,
						4,
						0
					],
					[
						52800,
						7,
						0
					],
					[
						52971.4285714286,
						4,
						0
					],
					[
						53314.2857142857,
						5,
						0
					],
					[
						53142.8571428572,
						1,
						171.428571428571
					],
					[
						52285.7142857143,
						6,
						0
					]
				],
				"mustHitSection": true
			},
			{
				"lengthInSteps": 16,
				"sectionNotes": [
					[
						53485.7142857143,
						3,
						600
					],
					[
						54171.4285714286,
						0,
						600
					],
					[
						54000,
						4,
						0
					],
					[
						54171.4285714286,
						7,
						0
					],
					[
						54342.8571428572,
						5,
						0
					],
					[
						54685.7142857143,
						7,
						0
					]
				],
				"mustHitSection": true
			},
			{
				"lengthInSteps": 16,
				"sectionNotes": [
					[
						54857.1428571429,
						2,
						600
					],
					[
						55542.8571428572,
						1,
						600
					],
					[
						54857.1428571429,
						6,
						0
					],
					[
						55200,
						7,
						0
					],
					[
						55542.8571428572,
						6,
						0
					],
					[
						55714.2857142857,
						4,
						0
					],
					[
						56057.1428571429,
						7,
						0
					]
				],
				"mustHitSection": true
			},
			{
				"lengthInSteps": 16,
				"sectionNotes": [
					[
						56228.5714285714,
						2,
						1285.71428571429
					],
					[
						56742.8571428572,
						6,
						0
					],
					[
						56400,
						4,
						0
					],
					[
						57085.7142857143,
						7,
						0
					],
					[
						57257.1428571429,
						6,
						0
					]
				],
				"mustHitSection": true
			},
			{
				"lengthInSteps": 16,
				"sectionNotes": [
					[
						57771.4285714286,
						0,
						0
					],
					[
						58114.2857142857,
						3,
						0
					],
					[
						58457.1428571429,
						0,
						0
					],
					[
						58628.5714285714,
						2,
						0
					]
				],
				"mustHitSection": false
			},
			{
				"lengthInSteps": 16,
				"sectionNotes": [
					[
						59142.8571428572,
						0,
						0
					],
					[
						59657.1428571429,
						1,
						0
					],
					[
						60000,
						0,
						0
					],
					[
						60171.4285714286,
						2,
						0
					],
					[
						59485.7142857143,
						2,
						0
					]
				],
				"mustHitSection": false
			},
			{
				"lengthInSteps": 16,
				"sectionNotes": [
					[
						60857.1428571429,
						0,
						428.571428571428
					],
					[
						61371.4285714286,
						3,
						257.142857142857
					],
					[
						60342.8571428572,
						5,
						0
					],
					[
						60685.7142857143,
						4,
						0
					],
					[
						60857.1428571429,
						7,
						0
					],
					[
						61200,
						7,
						0
					],
					[
						61371.4285714286,
						4,
						0
					]
				],
				"mustHitSection": true
			},
			{
				"lengthInSteps": 16,
				"sectionNotes": [
					[
						61885.7142857143,
						0,
						1114.28571428571
					],
					[
						61885.7142857143,
						5,
						0
					],
					[
						62057.1428571429,
						4,
						171.428571428571
					],
					[
						62400,
						4,
						0
					],
					[
						62742.8571428572,
						5,
						0
					],
					[
						61714.2857142857,
						0,
						0
					]
				],
				"mustHitSection": true
			},
			{
				"lengthInSteps": 16,
				"sectionNotes": [
					[
						63600,
						3,
						0
					],
					[
						63942.8571428572,
						0,
						428.571428571429
					],
					[
						63085.7142857143,
						5,
						0
					],
					[
						64114.2857142857,
						5,
						0
					],
					[
						64285.7142857143,
						4,
						0
					],
					[
						63428.5714285715,
						4,
						0
					],
					[
						63771.4285714286,
						7,
						0
					]
				],
				"mustHitSection": true
			},
			{
				"lengthInSteps": 16,
				"sectionNotes": [
					[
						64457.1428571429,
						2,
						600
					],
					[
						65142.8571428572,
						3,
						514.285714285714
					],
					[
						65485.7142857143,
						5,
						0
					],
					[
						65657.1428571429,
						1,
						428.571428571428
					],
					[
						64628.5714285715,
						5,
						0
					],
					[
						64800,
						4,
						0
					],
					[
						65142.8571428572,
						7,
						0
					]
				],
				"mustHitSection": true
			},
			{
				"lengthInSteps": 16,
				"sectionNotes": [
					[
						66342.8571428572,
						2,
						857.142857142857
					],
					[
						65828.5714285714,
						6,
						0
					],
					[
						66171.4285714286,
						4,
						0
					],
					[
						66514.2857142857,
						7,
						0
					],
					[
						66685.7142857143,
						4,
						0
					],
					[
						67028.5714285714,
						6,
						0
					]
				],
				"mustHitSection": true
			},
			{
				"lengthInSteps": 16,
				"sectionNotes": [
					[
						67714.2857142857,
						0,
						0
					],
					[
						68400,
						3,
						0
					],
					[
						67885.7142857143,
						1,
						0
					]
				],
				"mustHitSection": true
			},
			{
				"lengthInSteps": 16,
				"sectionNotes": [
					[
						68742.8571428571,
						1,
						0
					],
					[
						69085.7142857143,
						2,
						0
					],
					[
						69771.4285714286,
						3,
						857.142857142857
					],
					[
						69428.5714285714,
						3,
						0
					]
				],
				"mustHitSection": true
			},
			{
				"lengthInSteps": 16,
				"sectionNotes": [
					[
						70800,
						3,
						0
					],
					[
						71142.8571428571,
						0,
						600
					]
				],
				"mustHitSection": true
			},
			{
				"lengthInSteps": 16,
				"sectionNotes": [
					[
						72000,
						1,
						0
					],
					[
						72342.8571428571,
						0,
						0
					]
				],
				"mustHitSection": true
			},
			{
				"lengthInSteps": 16,
				"sectionNotes": [
					[
						72685.7142857143,
						6,
						0
					],
					[
						73200,
						4,
						771.428571428571
					],
					[
						73200,
						3,
						0
					],
					[
						73542.8571428571,
						2,
						0
					],
					[
						73714.2857142857,
						0,
						0
					],
					[
						72857.1428571428,
						1,
						0
					]
				],
				"mustHitSection": false
			},
			{
				"lengthInSteps": 16,
				"sectionNotes": [
					[
						74571.4285714286,
						5,
						428.571428571429
					],
					[
						75085.7142857143,
						7,
						257.142857142857
					],
					[
						74228.5714285714,
						2,
						0
					],
					[
						74571.4285714286,
						3,
						0
					],
					[
						74742.8571428571,
						0,
						0
					],
					[
						75085.7142857143,
						2,
						0
					]
				],
				"mustHitSection": false
			},
			{
				"lengthInSteps": 16,
				"sectionNotes": [
					[
						75428.5714285714,
						4,
						342.857142857143
					],
					[
						76628.5714285714,
						5,
						771.428571428571
					],
					[
						76114.2857142857,
						3,
						0
					],
					[
						75942.8571428571,
						2,
						0
					],
					[
						75600,
						1,
						0
					],
					[
						76457.1428571428,
						0,
						0
					],
					[
						76457.1428571428,
						5,
						0
					]
				],
				"mustHitSection": false
			},
			{
				"lengthInSteps": 16,
				"sectionNotes": [
					[
						76971.4285714285,
						0,
						0
					],
					[
						76800,
						1,
						0
					],
					[
						78000,
						2,
						0
					],
					[
						77828.5714285714,
						1,
						0
					],
					[
						77485.7142857143,
						0,
						0
					],
					[
						77314.2857142857,
						2,
						0
					]
				],
				"mustHitSection": false
			},
			{
				"lengthInSteps": 16,
				"sectionNotes": [
					[
						78685.7142857142,
						3,
						0
					],
					[
						79371.4285714285,
						3,
						0
					],
					[
						79028.5714285714,
						0,
						0
					]
				],
				"mustHitSection": true
			},
			{
				"lengthInSteps": 16,
				"sectionNotes": [
					[
						79714.2857142857,
						2,
						600
					]
				],
				"mustHitSection": true
			},
			{
				"lengthInSteps": 16,
				"sectionNotes": [
					[
						81428.5714285714,
						0,
						0
					],
					[
						82114.2857142857,
						0,
						0
					],
					[
						81600,
						1,
						0
					]
				],
				"mustHitSection": true
			},
			{
				"lengthInSteps": 16,
				"sectionNotes": [
					[
						82457.1428571428,
						3,
						428.571428571429
					],
					[
						83314.2857142857,
						3,
						257.142857142857
					]
				],
				"mustHitSection": true
			},
			{
				"lengthInSteps": 16,
				"sectionNotes": [
					[
						83657.1428571428,
						4,
						342.857142857143
					],
					[
						84171.4285714285,
						1,
						0
					],
					[
						84171.4285714285,
						6,
						814.285714285714
					],
					[
						83828.5714285714,
						0,
						0
					],
					[
						84514.2857142857,
						3,
						0
					],
					[
						84857.1428571428,
						2,
						0
					]
				],
				"mustHitSection": false
			},
			{
				"lengthInSteps": 16,
				"sectionNotes": [
					[
						85542.8571428571,
						5,
						428.571428571429
					],
					[
						86057.1428571428,
						7,
						257.142857142857
					],
					[
						85028.5714285714,
						2,
						0
					],
					[
						85371.4285714285,
						0,
						0
					],
					[
						86057.1428571428,
						1,
						0
					],
					[
						86228.5714285714,
						3,
						0
					],
					[
						85714.2857142857,
						2,
						0
					]
				],
				"mustHitSection": false
			},
			{
				"lengthInSteps": 16,
				"sectionNotes": [
					[
						86399.9999999999,
						3,
						600
					],
					[
						87085.7142857142,
						2,
						428.571428571428
					],
					[
						87599.9999999999,
						0,
						600
					],
					[
						86571.4285714285,
						4,
						0
					],
					[
						86914.2857142856,
						5,
						0
					],
					[
						87257.1428571428,
						7,
						0
					],
					[
						87599.9999999999,
						5,
						0
					]
				],
				"mustHitSection": true
			},
			{
				"lengthInSteps": 16,
				"sectionNotes": [
					[
						88285.7142857142,
						3,
						428.571428571429
					],
					[
						88799.9999999999,
						1,
						257.142857142857
					],
					[
						87942.8571428571,
						5,
						0
					],
					[
						88285.7142857142,
						6,
						0
					],
					[
						88799.9999999999,
						5,
						0
					],
					[
						87771.4285714285,
						4,
						0
					],
					[
						88628.5714285713,
						6,
						0
					]
				],
				"mustHitSection": true
			},
			{
				"sectionNotes": [
					[
						89142.8571428571,
						1,
						1114.28571428571
					],
					[
						90342.8571428571,
						2,
						857.142857142857
					],
					[
						90342.8571428571,
						6,
						0
					],
					[
						89657.1428571428,
						4,
						0
					],
					[
						89828.5714285713,
						7,
						0
					],
					[
						89999.9999999999,
						5,
						0
					]
				],
				"typeOfSection": 0,
				"lengthInSteps": 16,
				"gfSection": false,
				"altAnim": false,
				"mustHitSection": true,
				"changeBPM": false,
				"bpm": 180
			},
			{
				"sectionNotes": [
					[
						91371.4285714285,
						3,
						0
					],
					[
						91714.2857142856,
						1,
						0
					],
					[
						90685.7142857142,
						6,
						0
					],
					[
						91028.5714285713,
						4,
						0
					],
					[
						91199.9999999999,
						7,
						0
					],
					[
						91371.4285714285,
						4,
						0
					],
					[
						91714.2857142856,
						5,
						0
					]
				],
				"typeOfSection": 0,
				"lengthInSteps": 16,
				"gfSection": false,
				"altAnim": false,
				"mustHitSection": true,
				"changeBPM": false,
				"bpm": 175
			},
			{
				"sectionNotes": [
					[
						91885.7142857142,
						0,
						0
					],
					[
						92571.4285714285,
						0,
						0
					],
					[
						92399.9999999999,
						4,
						0
					],
					[
						92571.4285714285,
						7,
						0
					],
					[
						92742.857142857,
						5,
						0
					],
					[
						93085.7142857142,
						6,
						0
					],
					[
						92228.5714285713,
						1,
						0
					],
					[
						92914.2857142856,
						1,
						0
					]
				],
				"typeOfSection": 0,
				"lengthInSteps": 16,
				"gfSection": false,
				"altAnim": false,
				"mustHitSection": true,
				"changeBPM": false,
				"bpm": 175
			},
			{
				"sectionNotes": [
					[
						93428.5714285713,
						2,
						514.285714285714
					],
					[
						94285.7142857142,
						1,
						257.142857142857
					],
					[
						93942.857142857,
						4,
						0
					],
					[
						94285.7142857142,
						4,
						0
					],
					[
						94457.1428571428,
						5,
						0
					],
					[
						93257.1428571428,
						7,
						0
					],
					[
						93599.9999999999,
						7,
						0
					]
				],
				"typeOfSection": 0,
				"lengthInSteps": 16,
				"gfSection": false,
				"altAnim": false,
				"mustHitSection": true,
				"changeBPM": false,
				"bpm": 175
			},
			{
				"sectionNotes": [
					[
						94628.5714285713,
						5,
						1114.28571428571
					],
					[
						95828.5714285713,
						6,
						600
					],
					[
						94628.5714285713,
						2,
						0
					],
					[
						94885.7142857142,
						3,
						0
					],
					[
						95314.2857142856,
						3,
						0
					],
					[
						95657.1428571428,
						1,
						0
					],
					[
						95142.857142857,
						1,
						0
					],
					[
						94799.9999999999,
						1,
						0
					]
				],
				"typeOfSection": 0,
				"lengthInSteps": 16,
				"gfSection": false,
				"altAnim": false,
				"mustHitSection": false,
				"changeBPM": false,
				"bpm": 175
			},
			{
				"sectionNotes": [
					[
						96514.2857142856,
						4,
						428.571428571429
					],
					[
						97028.5714285713,
						6,
						257.142857142857
					],
					[
						95999.9999999999,
						2,
						0
					],
					[
						96171.4285714284,
						0,
						0
					],
					[
						97199.9999999999,
						1,
						0
					],
					[
						96514.2857142856,
						2,
						0
					],
					[
						96857.1428571427,
						3,
						0
					]
				],
				"typeOfSection": 0,
				"lengthInSteps": 16,
				"gfSection": false,
				"altAnim": false,
				"mustHitSection": false,
				"changeBPM": false,
				"bpm": 175
			},
			{
				"sectionNotes": [
					[
						97371.4285714284,
						5,
						1714.28571428571
					],
					[
						97885.7142857142,
						1,
						0
					],
					[
						97542.857142857,
						1,
						0
					],
					[
						98057.1428571427,
						3,
						0
					],
					[
						98399.9999999999,
						0,
						0
					]
				],
				"typeOfSection": 0,
				"lengthInSteps": 16,
				"gfSection": false,
				"altAnim": false,
				"mustHitSection": false,
				"changeBPM": false,
				"bpm": 175
			},
			{
				"sectionNotes": [
					[
						99257.1428571427,
						7,
						0
					],
					[
						99771.4285714284,
						6,
						0
					],
					[
						98742.857142857,
						1,
						0
					],
					[
						99085.7142857142,
						0,
						0
					],
					[
						99257.1428571427,
						1,
						0
					],
					[
						99771.4285714284,
						1,
						0
					],
					[
						99599.9999999999,
						3,
						0
					]
				],
				"typeOfSection": 0,
				"lengthInSteps": 16,
				"gfSection": false,
				"altAnim": false,
				"mustHitSection": false,
				"changeBPM": false,
				"bpm": 175
			},
			{
				"sectionNotes": [
					[
						100114.285714286,
						1,
						257.142857142857
					],
					[
						100971.428571428,
						0,
						257.142857142857
					],
					[
						100628.571428571,
						3,
						0
					],
					[
						101314.285714286,
						2,
						0
					]
				],
				"typeOfSection": 0,
				"lengthInSteps": 16,
				"gfSection": false,
				"altAnim": false,
				"mustHitSection": true,
				"changeBPM": false,
				"bpm": 175
			},
			{
				"sectionNotes": [
					[
						101657.142857143,
						3,
						0
					],
					[
						102000,
						0,
						0
					],
					[
						102342.857142857,
						2,
						514.285714285714
					]
				],
				"typeOfSection": 0,
				"lengthInSteps": 16,
				"gfSection": false,
				"altAnim": false,
				"mustHitSection": true,
				"changeBPM": false,
				"bpm": 175
			},
			{
				"sectionNotes": [
					[
						103028.571428571,
						3,
						0
					],
					[
						103885.714285714,
						2,
						0
					],
					[
						103371.428571428,
						0,
						0
					]
				],
				"typeOfSection": 0,
				"lengthInSteps": 16,
				"gfSection": false,
				"altAnim": false,
				"mustHitSection": true,
				"changeBPM": false,
				"bpm": 175
			},
			{
				"sectionNotes": [
					[
						104228.571428571,
						0,
						0
					],
					[
						104742.857142857,
						3,
						0
					],
					[
						105085.714285714,
						2,
						428.571428571429
					]
				],
				"typeOfSection": 0,
				"lengthInSteps": 16,
				"gfSection": false,
				"altAnim": false,
				"mustHitSection": true,
				"changeBPM": false,
				"bpm": 175
			},
			{
				"sectionNotes": [
					[
						105600,
						3,
						257.142857142857
					],
					[
						106114.285714286,
						1,
						771.428571428571
					],
					[
						106114.285714286,
						4,
						0
					],
					[
						106285.714285714,
						7,
						0
					],
					[
						106457.142857143,
						5,
						0
					],
					[
						106800,
						6,
						0
					]
				],
				"typeOfSection": 0,
				"lengthInSteps": 16,
				"gfSection": false,
				"altAnim": false,
				"mustHitSection": true,
				"changeBPM": false,
				"bpm": 175
			},
			{
				"sectionNotes": [
					[
						107485.714285714,
						3,
						257.142857142857
					],
					[
						108000,
						1,
						257.142857142857
					],
					[
						107142.857142857,
						6,
						0
					],
					[
						107485.714285714,
						4,
						0
					],
					[
						107657.142857143,
						7,
						0
					],
					[
						107828.571428571,
						4,
						0
					],
					[
						108171.428571428,
						5,
						0
					]
				],
				"typeOfSection": 0,
				"lengthInSteps": 16,
				"gfSection": false,
				"altAnim": false,
				"mustHitSection": true,
				"changeBPM": false,
				"bpm": 175
			},
			{
				"sectionNotes": [
					[
						108342.857142857,
						3,
						600
					],
					[
						109028.571428571,
						2,
						600
					],
					[
						108857.142857143,
						4,
						0
					],
					[
						109028.571428571,
						7,
						0
					],
					[
						109200,
						5,
						0
					],
					[
						109542.857142857,
						4,
						0
					]
				],
				"typeOfSection": 0,
				"lengthInSteps": 16,
				"gfSection": false,
				"altAnim": false,
				"mustHitSection": true,
				"changeBPM": false,
				"bpm": 175
			},
			{
				"sectionNotes": [
					[
						109714.285714286,
						0,
						600
					],
					[
						110400,
						1,
						600
					],
					[
						109714.285714286,
						7,
						0
					],
					[
						109885.714285714,
						5,
						0
					],
					[
						110228.571428571,
						4,
						0
					],
					[
						110571.428571428,
						5,
						0
					],
					[
						110742.857142857,
						6,
						0
					],
					[
						110914.285714286,
						5,
						0
					]
				],
				"typeOfSection": 0,
				"lengthInSteps": 16,
				"gfSection": false,
				"altAnim": false,
				"mustHitSection": true,
				"changeBPM": false,
				"bpm": 175
			},
			{
				"sectionNotes": [
					[
						111085.714285714,
						2,
						1371.42857142857
					]
				],
				"typeOfSection": 0,
				"lengthInSteps": 16,
				"gfSection": false,
				"altAnim": false,
				"mustHitSection": true,
				"changeBPM": false,
				"bpm": 175
			},
			{
				"sectionNotes": [
					[
						112457.142857143,
						0,
						0,
						"Makarakarn Note"
					],
					[
						113142.857142857,
						2,
						0,
						"Makarakarn Note"
					]
				],
				"typeOfSection": 0,
				"lengthInSteps": 16,
				"gfSection": false,
				"altAnim": false,
				"mustHitSection": true,
				"changeBPM": false,
				"bpm": 175
			},
			{
				"sectionNotes": [
					[
						113828.571428571,
						0,
						0,
						"Makarakarn Note"
					],
					[
						114171.428571428,
						1,
						0,
						"Makarakarn Note"
					],
					[
						114857.142857143,
						3,
						0,
						"Makarakarn Note"
					]
				],
				"typeOfSection": 0,
				"lengthInSteps": 16,
				"gfSection": false,
				"altAnim": false,
				"mustHitSection": true,
				"changeBPM": false,
				"bpm": 175
			},
			{
				"sectionNotes": [
					[
						115200,
						1,
						0,
						"Makarakarn Note"
					],
					[
						115885.714285714,
						0,
						0,
						"Makarakarn Note"
					]
				],
				"typeOfSection": 0,
				"lengthInSteps": 16,
				"gfSection": false,
				"altAnim": false,
				"mustHitSection": true,
				"changeBPM": false,
				"bpm": 175
			},
			{
				"sectionNotes": [
					[
						116571.428571428,
						0,
						0,
						"Makarakarn Note"
					],
					[
						116914.285714286,
						0,
						0,
						"Makarakarn Note"
					],
					[
						117257.142857143,
						3,
						0,
						"Makarakarn Note"
					]
				],
				"typeOfSection": 0,
				"lengthInSteps": 16,
				"gfSection": false,
				"altAnim": false,
				"mustHitSection": true,
				"changeBPM": false,
				"bpm": 175
			},
			{
				"sectionNotes": [
					[
						117942.857142857,
						0,
						0,
						"Makarakarn Note"
					],
					[
						118628.571428571,
						2,
						0,
						"Makarakarn Note"
					]
				],
				"typeOfSection": 0,
				"lengthInSteps": 16,
				"gfSection": false,
				"altAnim": false,
				"mustHitSection": true,
				"changeBPM": false,
				"bpm": 175
			},
			{
				"sectionNotes": [
					[
						119314.285714286,
						0,
						0,
						"Makarakarn Note"
					],
					[
						119657.142857143,
						1,
						0,
						"Makarakarn Note"
					],
					[
						120342.857142857,
						3,
						0,
						"Makarakarn Note"
					]
				],
				"typeOfSection": 0,
				"lengthInSteps": 16,
				"gfSection": false,
				"altAnim": false,
				"mustHitSection": true,
				"changeBPM": false,
				"bpm": 175
			},
			{
				"sectionNotes": [
					[
						121714.285714285,
						2,
						0
					],
					[
						120685.714285714,
						1,
						0,
						"Makarakarn Note"
					],
					[
						121371.428571428,
						0,
						0,
						"Makarakarn Note"
					]
				],
				"typeOfSection": 0,
				"lengthInSteps": 16,
				"gfSection": false,
				"altAnim": false,
				"mustHitSection": true,
				"changeBPM": false,
				"bpm": 175
			},
			{
				"sectionNotes": [
					[
						123085.714285714,
						1,
						0
					],
					[
						123257.142857143,
						2,
						257.142857142857
					],
					[
						122057.142857143,
						0,
						0
					],
					[
						122571.428571428,
						3,
						0
					]
				],
				"typeOfSection": 0,
				"lengthInSteps": 16,
				"gfSection": false,
				"altAnim": false,
				"mustHitSection": true,
				"changeBPM": false,
				"bpm": 175
			},
			{
				"sectionNotes": [
					[
						123942.857142857,
						3,
						0
					],
					[
						124315.714285714,
						1,
						342.857142857143
					],
					[
						123600,
						0,
						0
					]
				],
				"typeOfSection": 0,
				"lengthInSteps": 16,
				"gfSection": false,
				"altAnim": false,
				"mustHitSection": true,
				"changeBPM": false,
				"bpm": 175
			},
			{
				"sectionNotes": [
					[
						124800,
						3,
						0
					],
					[
						125657.142857143,
						2,
						0
					],
					[
						126000,
						0,
						257.142857142857
					],
					[
						125314.285714285,
						1,
						0
					]
				],
				"typeOfSection": 0,
				"lengthInSteps": 16,
				"gfSection": false,
				"altAnim": false,
				"mustHitSection": true,
				"changeBPM": false,
				"bpm": 175
			},
			{
				"sectionNotes": [
					[
						127200,
						2,
						257.142857142857
					],
					[
						126342.857142857,
						2,
						600
					]
				],
				"typeOfSection": 0,
				"lengthInSteps": 16,
				"gfSection": false,
				"altAnim": false,
				"mustHitSection": true,
				"changeBPM": false,
				"bpm": 175
			},
			{
				"sectionNotes": [
					[
						127542.857142857,
						3,
						257.142857142857
					],
					[
						128057.142857143,
						0,
						1200
					]
				],
				"typeOfSection": 0,
				"lengthInSteps": 16,
				"gfSection": false,
				"altAnim": false,
				"mustHitSection": true,
				"changeBPM": false,
				"bpm": 175
			},
			{
				"sectionNotes": [
					[
						129428.571428571,
						1,
						0
					],
					[
						129942.857142857,
						3,
						0
					]
				],
				"typeOfSection": 0,
				"lengthInSteps": 16,
				"gfSection": false,
				"altAnim": false,
				"mustHitSection": true,
				"changeBPM": false,
				"bpm": 175
			},
			{
				"sectionNotes": [
					[
						130285.714285714,
						2,
						1114.28571428571
					],
					[
						131485.714285714,
						3,
						514.285714285714
					]
				],
				"typeOfSection": 0,
				"lengthInSteps": 16,
				"gfSection": false,
				"altAnim": false,
				"mustHitSection": true,
				"changeBPM": false,
				"bpm": 175
			},
			{
				"sectionNotes": [
					[
						132171.428571428,
						3,
						428.571428571429
					],
					[
						132685.714285714,
						1,
						257.142857142857
					]
				],
				"typeOfSection": 0,
				"lengthInSteps": 16,
				"gfSection": false,
				"altAnim": false,
				"mustHitSection": true,
				"changeBPM": false,
				"bpm": 175
			},
			{
				"sectionNotes": [
					[
						133028.571428571,
						1,
						1114.28571428571
					],
					[
						134228.571428571,
						2,
						942.857142857143
					],
					[
						133542.857142857,
						4,
						0
					],
					[
						133714.285714285,
						7,
						0
					],
					[
						133885.714285714,
						5,
						0
					],
					[
						134228.571428571,
						6,
						0
					]
				],
				"typeOfSection": 0,
				"lengthInSteps": 16,
				"gfSection": false,
				"altAnim": false,
				"mustHitSection": true,
				"changeBPM": false,
				"bpm": 175
			},
			{
				"sectionNotes": [
					[
						135257.142857143,
						0,
						0
					],
					[
						135600,
						1,
						0
					],
					[
						134571.428571428,
						6,
						0
					],
					[
						134914.285714285,
						4,
						0
					],
					[
						135085.714285714,
						7,
						0
					],
					[
						135257.142857143,
						4,
						0
					],
					[
						135600,
						5,
						0
					]
				],
				"typeOfSection": 0,
				"lengthInSteps": 16,
				"gfSection": false,
				"altAnim": false,
				"mustHitSection": true,
				"changeBPM": false,
				"bpm": 175
			},
			{
				"sectionNotes": [
					[
						135771.428571428,
						3,
						0
					],
					[
						136114.285714285,
						0,
						0
					],
					[
						136285.714285714,
						4,
						0
					],
					[
						136457.142857143,
						7,
						0
					],
					[
						136628.571428571,
						5,
						0
					],
					[
						136971.428571428,
						6,
						0
					],
					[
						136457.142857143,
						1,
						0
					],
					[
						136800,
						2,
						0
					]
				],
				"typeOfSection": 0,
				"lengthInSteps": 16,
				"gfSection": false,
				"altAnim": false,
				"mustHitSection": true,
				"changeBPM": false,
				"bpm": 175
			},
			{
				"sectionNotes": [
					[
						138171.428571428,
						1,
						257.142857142857
					],
					[
						137142.857142857,
						4,
						0
					],
					[
						137314.285714285,
						5,
						0
					],
					[
						137314.285714285,
						3,
						685.714285714286
					],
					[
						137657.142857143,
						4,
						0
					],
					[
						138342.857142857,
						5,
						0
					],
					[
						138000,
						6,
						0
					],
					[
						138171.428571428,
						7,
						0
					]
				],
				"typeOfSection": 0,
				"lengthInSteps": 16,
				"gfSection": false,
				"altAnim": false,
				"mustHitSection": true,
				"changeBPM": false,
				"bpm": 175
			},
			{
				"sectionNotes": [
					[
						138514.285714285,
						5,
						1114.28571428571
					],
					[
						139714.285714285,
						6,
						600
					],
					[
						138514.285714285,
						0,
						0
					],
					[
						138685.714285714,
						1,
						0
					],
					[
						139028.571428571,
						2,
						0
					],
					[
						139542.857142857,
						1,
						0
					],
					[
						139371.428571428,
						0,
						0
					]
				],
				"typeOfSection": 0,
				"lengthInSteps": 16,
				"gfSection": false,
				"altAnim": false,
				"mustHitSection": false,
				"changeBPM": false,
				"bpm": 175
			},
			{
				"sectionNotes": [
					[
						140400,
						7,
						428.571428571429
					],
					[
						140914.285714285,
						6,
						257.142857142857
					],
					[
						140228.571428571,
						2,
						0
					],
					[
						139885.714285714,
						3,
						0
					],
					[
						140571.428571428,
						1,
						0
					],
					[
						140742.857142857,
						2,
						0
					],
					[
						141085.714285714,
						3,
						0
					]
				],
				"typeOfSection": 0,
				"lengthInSteps": 16,
				"gfSection": false,
				"altAnim": false,
				"mustHitSection": false,
				"changeBPM": false,
				"bpm": 175
			},
			{
				"sectionNotes": [
					[
						141257.142857143,
						4,
						1714.28571428571
					],
					[
						141428.571428571,
						2,
						0
					],
					[
						141771.428571428,
						0,
						0
					],
					[
						142114.285714286,
						0,
						0
					],
					[
						141942.857142857,
						3,
						0
					],
					[
						142285.714285714,
						1,
						0
					]
				],
				"typeOfSection": 0,
				"lengthInSteps": 16,
				"gfSection": false,
				"altAnim": false,
				"mustHitSection": false,
				"changeBPM": false,
				"bpm": 175
			},
			{
				"sectionNotes": [
					[
						143142.857142857,
						4,
						0
					],
					[
						143657.142857143,
						7,
						257.142857142857
					],
					[
						142971.428571428,
						3,
						0
					],
					[
						142628.571428571,
						0,
						0
					],
					[
						143314.285714286,
						1,
						0
					],
					[
						143657.142857143,
						0,
						0
					],
					[
						143142.857142857,
						0,
						0
					]
				],
				"typeOfSection": 0,
				"lengthInSteps": 16,
				"gfSection": false,
				"altAnim": false,
				"mustHitSection": false,
				"changeBPM": false,
				"bpm": 175
			},
			{
				"sectionNotes": [
					[
						144000,
						1,
						257.142857142857
					],
					[
						144857.142857143,
						3,
						0
					],
					[
						145200,
						2,
						0
					],
					[
						144514.285714286,
						2,
						0
					]
				],
				"typeOfSection": 0,
				"lengthInSteps": 16,
				"gfSection": false,
				"altAnim": false,
				"mustHitSection": true,
				"changeBPM": false,
				"bpm": 175
			},
			{
				"sectionNotes": [
					[
						145542.857142857,
						0,
						0
					],
					[
						145885.714285714,
						1,
						0
					],
					[
						146228.571428571,
						3,
						514.285714285714
					]
				],
				"typeOfSection": 0,
				"lengthInSteps": 16,
				"gfSection": false,
				"altAnim": false,
				"mustHitSection": true,
				"changeBPM": false,
				"bpm": 175
			},
			{
				"sectionNotes": [
					[
						146914.285714286,
						0,
						0
					],
					[
						147428.571428571,
						0,
						257.142857142857
					],
					[
						147257.142857143,
						3,
						0
					],
					[
						147771.428571428,
						2,
						0
					]
				],
				"typeOfSection": 0,
				"lengthInSteps": 16,
				"gfSection": false,
				"altAnim": false,
				"mustHitSection": true,
				"changeBPM": false,
				"bpm": 175
			},
			{
				"sectionNotes": [
					[
						148114.285714286,
						3,
						0
					],
					[
						148971.428571428,
						1,
						428.571428571429
					],
					[
						148628.571428571,
						0,
						0
					]
				],
				"typeOfSection": 0,
				"lengthInSteps": 16,
				"gfSection": false,
				"altAnim": false,
				"mustHitSection": true,
				"changeBPM": false,
				"bpm": 175
			},
			{
				"sectionNotes": [
					[
						149485.714285714,
						0,
						0
					],
					[
						150000,
						1,
						771.428571428571
					],
					[
						150000,
						4,
						0
					],
					[
						150171.428571428,
						7,
						0
					],
					[
						150342.857142857,
						5,
						0
					],
					[
						150685.714285714,
						6,
						0
					]
				],
				"typeOfSection": 0,
				"lengthInSteps": 16,
				"gfSection": false,
				"altAnim": false,
				"mustHitSection": true,
				"changeBPM": false,
				"bpm": 175
			},
			{
				"sectionNotes": [
					[
						151885.714285714,
						1,
						257.142857142857
					],
					[
						151028.571428571,
						6,
						0
					],
					[
						151371.428571428,
						4,
						0
					],
					[
						151542.857142857,
						7,
						0
					],
					[
						151714.285714286,
						4,
						0
					],
					[
						152057.142857143,
						5,
						0
					],
					[
						151371.428571428,
						3,
						0
					]
				],
				"typeOfSection": 0,
				"lengthInSteps": 16,
				"gfSection": false,
				"altAnim": false,
				"mustHitSection": true,
				"changeBPM": false,
				"bpm": 175
			},
			{
				"sectionNotes": [
					[
						152228.571428571,
						3,
						600
					],
					[
						152914.285714286,
						2,
						600
					],
					[
						152742.857142857,
						4,
						0
					],
					[
						152914.285714286,
						7,
						0
					],
					[
						153085.714285714,
						5,
						0
					],
					[
						153428.571428571,
						7,
						0
					]
				],
				"typeOfSection": 0,
				"lengthInSteps": 16,
				"gfSection": false,
				"altAnim": false,
				"mustHitSection": true,
				"changeBPM": false,
				"bpm": 175
			},
			{
				"sectionNotes": [
					[
						153600,
						0,
						600
					],
					[
						154285.714285714,
						1,
						600
					],
					[
						153600,
						4,
						0
					],
					[
						153771.428571428,
						6,
						0
					],
					[
						154800,
						5,
						0
					],
					[
						154457.142857143,
						7,
						0
					],
					[
						154114.285714286,
						5,
						0
					]
				],
				"typeOfSection": 0,
				"lengthInSteps": 16,
				"gfSection": false,
				"altAnim": false,
				"mustHitSection": true,
				"changeBPM": false,
				"bpm": 175
			},
			{
				"sectionNotes": [
					[
						154971.428571428,
						2,
						1285.71428571429
					],
					[
						155485.714285714,
						7,
						0
					],
					[
						155657.142857143,
						4,
						0
					],
					[
						155142.857142857,
						5,
						0
					],
					[
						156000,
						6,
						0
					]
				],
				"typeOfSection": 0,
				"lengthInSteps": 16,
				"gfSection": false,
				"altAnim": false,
				"mustHitSection": true,
				"changeBPM": false,
				"bpm": 175
			},
			{
				"sectionNotes": [
					[
						156514.285714286,
						0,
						0
					],
					[
						156857.142857143,
						1,
						0
					],
					[
						157028.571428571,
						2,
						0
					],
					[
						157371.428571428,
						1,
						171.428571428571
					],
					[
						157371.428571428,
						5,
						0,
						"Makarakarn Note"
					],
					[
						157028.571428571,
						6,
						0,
						"Makarakarn Note"
					]
				],
				"typeOfSection": 0,
				"lengthInSteps": 16,
				"gfSection": false,
				"altAnim": false,
				"mustHitSection": false,
				"changeBPM": false,
				"bpm": 175
			},
			{
				"sectionNotes": [
					[
						157885.714285714,
						0,
						0
					],
					[
						158228.571428571,
						1,
						0
					],
					[
						158400,
						2,
						0
					],
					[
						158742.857142857,
						1,
						0
					],
					[
						158914.285714286,
						3,
						0
					],
					[
						158400,
						6,
						0,
						"Makarakarn Note"
					],
					[
						158571.428571428,
						4,
						0,
						"Makarakarn Note"
					],
					[
						158742.857142857,
						5,
						0,
						"Makarakarn Note"
					]
				],
				"typeOfSection": 0,
				"lengthInSteps": 16,
				"gfSection": false,
				"altAnim": false,
				"mustHitSection": false,
				"changeBPM": false,
				"bpm": 175
			},
			{
				"sectionNotes": [
					[
						159085.714285714,
						1,
						0
					],
					[
						159428.571428571,
						0,
						0
					],
					[
						159771.428571428,
						3,
						0
					],
					[
						159942.857142857,
						0,
						0
					],
					[
						160114.285714286,
						2,
						0
					],
					[
						159771.428571428,
						7,
						0,
						"Makarakarn Note"
					],
					[
						159428.571428571,
						4,
						0,
						"Makarakarn Note"
					],
					[
						160114.285714286,
						6,
						0,
						"Makarakarn Note"
					],
					[
						159942.857142857,
						4,
						0,
						"Makarakarn Note"
					]
				],
				"typeOfSection": 0,
				"lengthInSteps": 16,
				"gfSection": false,
				"altAnim": false,
				"mustHitSection": false,
				"changeBPM": false,
				"bpm": 175
			},
			{
				"sectionNotes": [
					[
						161657.142857143,
						1,
						257.142857142857
					],
					[
						160628.571428571,
						5,
						85.7142857142857
					],
					[
						160800,
						4,
						85.7142857142857
					],
					[
						161142.857142857,
						4,
						0
					],
					[
						160800,
						3,
						0,
						"Makarakarn Note"
					],
					[
						160457.142857143,
						1,
						0
					],
					[
						161142.857142857,
						0,
						0
					],
					[
						161485.714285714,
						7,
						0
					]
				],
				"typeOfSection": 0,
				"lengthInSteps": 16,
				"gfSection": false,
				"altAnim": false,
				"mustHitSection": true,
				"changeBPM": false,
				"bpm": 175
			},
			{
				"sectionNotes": [
					[
						162000,
						3,
						171.428571428571
					],
					[
						162342.857142857,
						0,
						85.7142857142857
					],
					[
						162685.714285714,
						2,
						342.857142857143
					],
					[
						162514.285714286,
						7,
						0
					],
					[
						162685.714285714,
						4,
						0
					],
					[
						161828.571428571,
						6,
						0
					],
					[
						162171.428571428,
						5,
						0
					],
					[
						163028.571428571,
						7,
						0
					]
				],
				"typeOfSection": 0,
				"lengthInSteps": 16,
				"gfSection": false,
				"altAnim": false,
				"mustHitSection": true,
				"changeBPM": false,
				"bpm": 175
			},
			{
				"sectionNotes": [
					[
						163371.428571428,
						6,
						0
					],
					[
						163714.285714286,
						4,
						0
					],
					[
						163885.714285714,
						4,
						0
					],
					[
						164400,
						0,
						600
					],
					[
						164228.571428571,
						7,
						0
					],
					[
						164400,
						4,
						0
					],
					[
						163200,
						3,
						1114.28571428571
					]
				],
				"typeOfSection": 0,
				"lengthInSteps": 16,
				"gfSection": false,
				"altAnim": false,
				"mustHitSection": true,
				"changeBPM": false,
				"bpm": 175
			},
			{
				"sectionNotes": [
					[
						164571.428571428,
						6,
						0
					],
					[
						165600,
						4,
						0
					],
					[
						165771.428571428,
						4,
						0
					],
					[
						165085.714285714,
						1,
						771.428571428571
					],
					[
						164914.285714286,
						7,
						0
					],
					[
						165257.142857143,
						5,
						0
					]
				],
				"typeOfSection": 0,
				"lengthInSteps": 16,
				"gfSection": false,
				"altAnim": false,
				"mustHitSection": true,
				"changeBPM": false,
				"bpm": 175
			},
			{
				"sectionNotes": [
					[
						165942.857142857,
						3,
						0,
						"Makarakarn Note"
					],
					[
						165942.857142857,
						0,
						0,
						"Makarakarn Note"
					]
				],
				"typeOfSection": 0,
				"lengthInSteps": 16,
				"gfSection": false,
				"altAnim": false,
				"mustHitSection": true,
				"changeBPM": false,
				"bpm": 175
			},
			{
				"sectionNotes": [],
				"typeOfSection": 0,
				"lengthInSteps": 16,
				"gfSection": false,
				"altAnim": false,
				"mustHitSection": true,
				"changeBPM": false,
				"bpm": 175
			},
			{
				"lengthInSteps": 16,
				"typeOfSection": 0,
				"sectionNotes": [],
				"altAnim": false,
				"gfSection": false,
				"bpm": 175,
				"changeBPM": false,
				"mustHitSection": true
			},
			{
				"sectionNotes": [],
				"typeOfSection": 0,
				"lengthInSteps": 16,
				"gfSection": false,
				"altAnim": false,
				"mustHitSection": true,
				"changeBPM": false,
				"bpm": 175
			},
			{
				"lengthInSteps": 16,
				"typeOfSection": 0,
				"sectionNotes": [],
				"altAnim": false,
				"bpm": 175,
				"changeBPM": false,
				"mustHitSection": true
			},
			{
				"sectionNotes": [],
				"typeOfSection": 0,
				"lengthInSteps": 16,
				"altAnim": false,
				"mustHitSection": true,
				"changeBPM": false,
				"bpm": 175
			},
			{
				"sectionNotes": [],
				"typeOfSection": 0,
				"lengthInSteps": 16,
				"altAnim": false,
				"mustHitSection": true,
				"changeBPM": false,
				"bpm": 175
			},
			{
				"sectionNotes": [],
				"typeOfSection": 0,
				"lengthInSteps": 16,
				"altAnim": false,
				"mustHitSection": true,
				"changeBPM": false,
				"bpm": 175
			},
			{
				"sectionNotes": [],
				"typeOfSection": 0,
				"lengthInSteps": 16,
				"altAnim": false,
				"mustHitSection": true,
				"changeBPM": false,
				"bpm": 175
			},
			{
				"sectionNotes": [],
				"typeOfSection": 0,
				"lengthInSteps": 16,
				"altAnim": false,
				"mustHitSection": true,
				"changeBPM": false,
				"bpm": 175
			},
			{
				"sectionNotes": [],
				"typeOfSection": 0,
				"lengthInSteps": 16,
				"altAnim": false,
				"mustHitSection": true,
				"changeBPM": false,
				"bpm": 175
			},
			{
				"sectionNotes": [],
				"typeOfSection": 0,
				"lengthInSteps": 16,
				"altAnim": false,
				"mustHitSection": true,
				"changeBPM": false,
				"bpm": 175
			},
			{
				"sectionNotes": [],
				"typeOfSection": 0,
				"lengthInSteps": 16,
				"altAnim": false,
				"mustHitSection": true,
				"changeBPM": false,
				"bpm": 175
			},
			{
				"lengthInSteps": 16,
				"typeOfSection": 0,
				"sectionNotes": [],
				"altAnim": false,
				"bpm": 175,
				"changeBPM": false,
				"mustHitSection": true
			},
			{
				"lengthInSteps": 16,
				"typeOfSection": 0,
				"sectionNotes": [],
				"altAnim": false,
				"bpm": 175,
				"changeBPM": false,
				"mustHitSection": true
			},
			{
				"sectionNotes": [],
				"typeOfSection": 0,
				"lengthInSteps": 16,
				"altAnim": false,
				"mustHitSection": true,
				"changeBPM": false,
				"bpm": 175
			},
			{
				"sectionNotes": [],
				"typeOfSection": 0,
				"lengthInSteps": 16,
				"altAnim": false,
				"mustHitSection": true,
				"changeBPM": false,
				"bpm": 175
			},
			{
				"lengthInSteps": 16,
				"typeOfSection": 0,
				"sectionNotes": [],
				"altAnim": false,
				"bpm": 175,
				"changeBPM": false,
				"mustHitSection": true
			},
			{
				"lengthInSteps": 16,
				"typeOfSection": 0,
				"sectionNotes": [],
				"altAnim": false,
				"bpm": 175,
				"changeBPM": false,
				"mustHitSection": true
			},
			{
				"sectionNotes": [],
				"typeOfSection": 0,
				"lengthInSteps": 16,
				"altAnim": false,
				"mustHitSection": true,
				"changeBPM": false,
				"bpm": 175
			},
			{
				"lengthInSteps": 16,
				"typeOfSection": 0,
				"sectionNotes": [],
				"altAnim": false,
				"bpm": 175,
				"changeBPM": false,
				"mustHitSection": true
			},
			{
				"sectionNotes": [],
				"typeOfSection": 0,
				"lengthInSteps": 16,
				"altAnim": false,
				"mustHitSection": true,
				"changeBPM": false,
				"bpm": 175
			},
			{
				"sectionNotes": [],
				"typeOfSection": 0,
				"lengthInSteps": 16,
				"altAnim": false,
				"mustHitSection": true,
				"changeBPM": false,
				"bpm": 175
			},
			{
				"sectionNotes": [],
				"typeOfSection": 0,
				"lengthInSteps": 16,
				"altAnim": false,
				"mustHitSection": true,
				"changeBPM": false,
				"bpm": 175
			},
			{
				"lengthInSteps": 16,
				"typeOfSection": 0,
				"sectionNotes": [],
				"altAnim": false,
				"bpm": 175,
				"changeBPM": false,
				"mustHitSection": true
			},
			{
				"sectionNotes": [],
				"typeOfSection": 0,
				"lengthInSteps": 16,
				"altAnim": false,
				"mustHitSection": true,
				"changeBPM": false,
				"bpm": 175
			},
			{
				"sectionNotes": [],
				"typeOfSection": 0,
				"lengthInSteps": 16,
				"altAnim": false,
				"mustHitSection": true,
				"changeBPM": false,
				"bpm": 175
			},
			{
				"sectionNotes": [],
				"typeOfSection": 0,
				"lengthInSteps": 16,
				"altAnim": false,
				"mustHitSection": true,
				"changeBPM": false,
				"bpm": 175
			},
			{
				"lengthInSteps": 16,
				"altAnim": false,
				"typeOfSection": 0,
				"sectionNotes": [],
				"bpm": 175,
				"changeBPM": false,
				"mustHitSection": true
			}
		],
		"gfVersion": "gf-metaverse",
		"events": [],
		"player3": "gf-metaverse",
		"song": "what you wish for",
		"validScore": true,
		"needsVoices": true,
		"arrowSkin": "",
		"stage": "metaverse",
		"speed": 2.2,
		"bpm": 175
	}
}